{
  "autoencoder": "flux_1_vae_f16.ckpt",
  "clip_encoder": "clip_vit_l14_f16.ckpt",
  "converted": {
    "988886_verusvision10b_10btransformer_q8p.ckpt": "902e58675b611141f78e6737fc53fb1a6928e29d6c4d0e591ec0308034d634a1"
  },
  "default_scale": 16,
  "file": "988886_verusvision10b_10btransformer_q8p.ckpt",
  "high_precision_autoencoder": true,
  "hires_fix_scale": 24,
  "modifier": "none",
  "name": "Verus_Vision10b_10b_Transformer",
  "noise_discretization": {
    "rf": {
      "_0": {
        "condition_scale": 1000,
        "sigma_max": 1,
        "sigma_min": 0
      }
    }
  },
  "objective": {
    "u": {
      "condition_scale": 1000
    }
  },
  "prefix": "",
  "text_encoder": "t5_xxl_encoder_q6p.ckpt",
  "upcast_attention": false,
  "version": "flux1"
}
