{
  "autoencoder": "flux_1_vae_f16.ckpt",
  "clip_encoder": "clip_vit_l14_f16.ckpt",
  "converted": {
    "845592_c4pacitor_dv1_q8p.ckpt": "a493251b9a29be401c4f5ec72d860bfed09fed0bbe4322117a057d2be519e07d"
  },
  "default_scale": 16,
  "file": "845592_c4pacitor_dv1_q8p.ckpt",
  "guidance_embed": true,
  "high_precision_autoencoder": true,
  "hires_fix_scale": 24,
  "modifier": "none",
  "name": "C4pacitor_d_V1",
  "noise_discretization": {
    "rf": {
      "_0": {
        "condition_scale": 1000,
        "sigma_max": 1,
        "sigma_min": 0
      }
    }
  },
  "objective": {
    "u": {
      "condition_scale": 1000
    }
  },
  "prefix": "",
  "text_encoder": "t5_xxl_encoder_q6p.ckpt",
  "upcast_attention": false,
  "version": "flux1"
}
